[
    {
        "x": 242.0,
        "y": 306.0,
        "angle": 1.486270303882067,
        "score": 0.8000338332727551,
        "class": 5.0
    },
    {
        "x": 188.0,
        "y": 301.0,
        "angle": 4.565013201874752,
        "score": 0.8035921283066273,
        "class": 4.0
    },
    {
        "x": 61.0,
        "y": 398.0,
        "angle": 1.5615720640311057,
        "score": 0.7996403614990413,
        "class": 4.0
    },
    {
        "x": 186.0,
        "y": 273.0,
        "angle": 1.3567302758829651,
        "score": 0.8019914796575904,
        "class": 4.0
    },
    {
        "x": 266.0,
        "y": 289.0,
        "angle": 1.2370396452594847,
        "score": 0.7986416151747108,
        "class": 5.0
    },
    {
        "x": 82.0,
        "y": 342.0,
        "angle": 1.5552037565263985,
        "score": 0.7980452830437571,
        "class": 4.0
    },
    {
        "x": 82.0,
        "y": 249.0,
        "angle": 1.8790650268158653,
        "score": 0.8141257926821709,
        "class": 2.0
    },
    {
        "x": 65.0,
        "y": 333.0,
        "angle": 1.7266837060757738,
        "score": 0.7975531631498598,
        "class": 4.0
    },
    {
        "x": 106.0,
        "y": 353.0,
        "angle": 1.3248847600185623,
        "score": 0.7970195758156479,
        "class": 4.0
    },
    {
        "x": 102.0,
        "y": 301.0,
        "angle": 2.1904818881047143,
        "score": 0.7952088521327824,
        "class": 2.0
    },
    {
        "x": 201.0,
        "y": 210.0,
        "angle": 0.5539425102856284,
        "score": 0.7951372754760087,
        "class": 4.0
    },
    {
        "x": 141.0,
        "y": 412.0,
        "angle": 0.6659473733208194,
        "score": 0.8765085995197296,
        "class": 2.0
    },
    {
        "x": 190.0,
        "y": 493.0,
        "angle": 0.7847025968006629,
        "score": 0.7941704336553812,
        "class": 5.0
    },
    {
        "x": 221.0,
        "y": 156.0,
        "angle": 0.8176329040551091,
        "score": 0.9720058083534241,
        "class": 4.0
    },
    {
        "x": 150.0,
        "y": 125.0,
        "angle": 2.764756446514218,
        "score": 0.7937110599130393,
        "class": 4.0
    },
    {
        "x": 116.0,
        "y": 501.0,
        "angle": 0.5244601053710096,
        "score": 0.9084815979003906,
        "class": 4.0
    },
    {
        "x": 243.0,
        "y": 350.0,
        "angle": 2.1978365858700384,
        "score": 0.7898099470650777,
        "class": 5.0
    },
    {
        "x": 154.0,
        "y": 301.0,
        "angle": 1.3985775644837668,
        "score": 0.9234335780143738,
        "class": 2.0
    },
    {
        "x": 234.0,
        "y": 321.0,
        "angle": 1.6980781636755102,
        "score": 0.7868499420117587,
        "class": 5.0
    },
    {
        "x": 52.0,
        "y": 213.0,
        "angle": 5.282623903161458,
        "score": 0.7871442588046194,
        "class": 2.0
    },
    {
        "x": 141.0,
        "y": 338.0,
        "angle": 1.1854645440971798,
        "score": 0.8678739368915558,
        "class": 2.0
    },
    {
        "x": 62.0,
        "y": 165.0,
        "angle": 2.217943538092429,
        "score": 0.8080900982022285,
        "class": 2.0
    },
    {
        "x": 165.0,
        "y": 476.0,
        "angle": 0.842188898179069,
        "score": 0.7855477062985301,
        "class": 4.0
    },
    {
        "x": 218.0,
        "y": 459.0,
        "angle": 6.129543708551671,
        "score": 0.7823223845334724,
        "class": 5.0
    },
    {
        "x": 194.0,
        "y": 141.0,
        "angle": 0.6894098993985163,
        "score": 0.7709299835376442,
        "class": 5.0
    },
    {
        "x": 209.0,
        "y": 194.0,
        "angle": 0.5756388912696151,
        "score": 0.9216271638870239,
        "class": 4.0
    },
    {
        "x": 237.0,
        "y": 398.0,
        "angle": 2.599902042404846,
        "score": 0.7650250710546971,
        "class": 5.0
    },
    {
        "x": 131.0,
        "y": 146.0,
        "angle": 5.81967320505793,
        "score": 0.7699109874665737,
        "class": 4.0
    },
    {
        "x": 130.0,
        "y": 194.0,
        "angle": 5.443319600503038,
        "score": 0.7581286731176078,
        "class": 4.0
    },
    {
        "x": 194.0,
        "y": 244.0,
        "angle": 3.7692705300391296,
        "score": 0.7525827090430539,
        "class": 5.0
    },
    {
        "x": 250.0,
        "y": 214.0,
        "angle": 0.7228927352771216,
        "score": 0.7518421201501042,
        "class": 5.0
    },
    {
        "x": 161.0,
        "y": 444.0,
        "angle": 0.34351967443542497,
        "score": 0.7510324429720641,
        "class": 2.0
    },
    {
        "x": 179.0,
        "y": 173.0,
        "angle": 2.96661779894636,
        "score": 0.7430965865030885,
        "class": 2.0
    },
    {
        "x": 155.0,
        "y": 150.0,
        "angle": 2.7114122341596723,
        "score": 0.7501949481666088,
        "class": 2.0
    },
    {
        "x": 150.0,
        "y": 220.0,
        "angle": 2.594861025987352,
        "score": 0.8170082807540894,
        "class": 4.0
    },
    {
        "x": 132.0,
        "y": 364.0,
        "angle": 1.077578371843101,
        "score": 0.8910519242286682,
        "class": 2.0
    },
    {
        "x": 77.0,
        "y": 452.0,
        "angle": 4.161392635640739,
        "score": 0.7316648085019551,
        "class": 4.0
    },
    {
        "x": 122.0,
        "y": 379.0,
        "angle": 1.13072416886579,
        "score": 0.8954312801361084,
        "class": 4.0
    },
    {
        "x": 43.0,
        "y": 435.0,
        "angle": 1.4075006825918002,
        "score": 0.7294867783319205,
        "class": 4.0
    },
    {
        "x": 138.0,
        "y": 498.0,
        "angle": 4.008217264887325,
        "score": 0.8630059480667114,
        "class": 2.0
    },
    {
        "x": 219.0,
        "y": 475.0,
        "angle": 0.14268505715575133,
        "score": 0.7165950208436698,
        "class": 5.0
    },
    {
        "x": 250.0,
        "y": 134.0,
        "angle": 0.8170479121315593,
        "score": 0.7070473927306011,
        "class": 5.0
    },
    {
        "x": 157.0,
        "y": 349.0,
        "angle": 0.9217921644100667,
        "score": 0.7400339722633362,
        "class": 2.0
    },
    {
        "x": 194.0,
        "y": 340.0,
        "angle": 3.675418706598306,
        "score": 0.6929913025349379,
        "class": 5.0
    },
    {
        "x": 262.0,
        "y": 422.0,
        "angle": 2.6363979772874497,
        "score": 0.6775763221085072,
        "class": 5.0
    },
    {
        "x": 58.0,
        "y": 253.0,
        "angle": 2.2903142276016086,
        "score": 0.6754556491039694,
        "class": 4.0
    },
    {
        "x": 154.0,
        "y": 181.0,
        "angle": 5.9151007527820205,
        "score": 0.6376040123403073,
        "class": 4.0
    },
    {
        "x": 203.0,
        "y": 477.0,
        "angle": 3.318950931753208,
        "score": 0.8049688458442688,
        "class": 5.0
    },
    {
        "x": 139.0,
        "y": 453.0,
        "angle": 3.5013868263474204,
        "score": 0.7701740980148315,
        "class": 2.0
    },
    {
        "x": 257.0,
        "y": 370.0,
        "angle": 5.524074333153784,
        "score": 0.58241472824011,
        "class": 5.0
    },
    {
        "x": 285.0,
        "y": 461.0,
        "angle": 5.942019225277818,
        "score": 0.5707403279840946,
        "class": 4.0
    },
    {
        "x": 98.0,
        "y": 109.0,
        "angle": 2.539119454472706,
        "score": 0.5524847284890712,
        "class": 2.0
    },
    {
        "x": 34.0,
        "y": 406.0,
        "angle": 1.8576984460289476,
        "score": 0.5321004622848704,
        "class": 4.0
    },
    {
        "x": 181.0,
        "y": 533.0,
        "angle": 0.7566401441824522,
        "score": 0.516887242719531,
        "class": 4.0
    }
]